{
  "holdings": [
    {
      "owner": "EF",
      "asset_type": "EQ",
      "account": "SIPP",
      "ticker": "VJPN",
      "name": "Japan",
      "quantity": 2167.0,
      "book_cost": 65855.0,
      "book_cost_per_unit": 30.38994000922935,
      "last_price": 37.162498474121094,
      "current_value": 80531.13419342041,
      "pl_pct": 22.29,
      "target_weight": 7.9,
      "auto_price": true,
      "price_updated": "2026-02-24T07:06:29.835152"
    },
    {
      "owner": "EF",
      "asset_type": "EQ",
      "account": "SIPP",
      "ticker": "CSWG",
      "name": "MSCI Switzerland",
      "quantity": 2347.0,
      "book_cost": 25486.0,
      "book_cost_per_unit": 10.85896889646357,
      "last_price": 12.005999755859374,
      "current_value": 28178.08142700195,
      "pl_pct": 10.56,
      "target_weight": 4.0,
      "auto_price": true,
      "price_updated": "2026-02-24T07:06:29.835152"
    },
    {
      "owner": "EF",
      "asset_type": "EQ",
      "account": "ISA",
      "ticker": "CSWG",
      "name": "MSCI Switzerland",
      "quantity": 940.0,
      "book_cost": 10207.0,
      "book_cost_per_unit": 10.858510638297872,
      "last_price": 12.005999755859374,
      "current_value": 11285.639770507812,
      "pl_pct": 10.57,
      "target_weight": 0.0,
      "auto_price": true,
      "price_updated": "2026-02-24T07:06:29.835152"
    },
    {
      "owner": "EF",
      "asset_type": "EQ",
      "account": "ISA",
      "ticker": "BRWM",
      "name": "Black Rock World Mining",
      "quantity": 3819.0,
      "book_cost": 22570.0,
      "book_cost_per_unit": 5.909924063891071,
      "last_price": 10.0,
      "current_value": 38190.0,
      "pl_pct": 69.21,
      "target_weight": 3.8,
      "auto_price": true,
      "price_updated": "2026-02-24T07:06:29.835152"
    },
    {
      "owner": "LF",
      "asset_type": "EQ",
      "account": "SIPP",
      "ticker": "AGT",
      "name": "AVI",
      "quantity": 21381.0,
      "book_cost": 47680.0,
      "book_cost_per_unit": 2.230017305083953,
      "last_price": 2.65,
      "current_value": 56659.65,
      "pl_pct": 18.83,
      "target_weight": 6.3,
      "auto_price": true,
      "price_updated": "2026-02-24T07:08:48.935038"
    },
    {
      "owner": "EF",
      "asset_type": "EQ",
      "account": "SIPP",
      "ticker": "B61ZBV3",
      "name": "Ranmore Global Equity",
      "quantity": 223.0,
      "book_cost": 32794.0,
      "book_cost_per_unit": 147.05829596412556,
      "last_price": 183.21,
      "current_value": 40855.83,
      "pl_pct": 24.58,
      "target_weight": 4.2,
      "auto_price": true,
      "price_updated": "2026-02-24T07:06:29.835152"
    },
    {
      "owner": "EF",
      "asset_type": "EQ",
      "account": "ISA",
      "ticker": "CSCA",
      "name": "Ishares Canada",
      "quantity": 143.0,
      "book_cost": 24433.0,
      "book_cost_per_unit": 170.86013986013987,
      "last_price": 217.34,
      "current_value": 31079.62,
      "pl_pct": 27.2,
      "target_weight": 3.2,
      "auto_price": true,
      "price_updated": "2026-02-24T07:06:29.835152"
    },
    {
      "owner": "LF",
      "asset_type": "EQ",
      "account": "SIPP",
      "ticker": "SPOG",
      "name": "Shares Oil & Gas Explr&Prod ETF USD Acc GBP",
      "quantity": 1404.0,
      "book_cost": 27997.0,
      "book_cost_per_unit": 19.94088319088319,
      "last_price": 23.345,
      "current_value": 32776.38,
      "pl_pct": 17.07,
      "target_weight": 3.0,
      "auto_price": true,
      "price_updated": "2026-02-24T07:06:29.835152"
    },
    {
      "owner": "EF",
      "asset_type": "MA",
      "account": "SIPP",
      "ticker": "CGT",
      "name": "Capital Gearing Trust",
      "quantity": 2187.0,
      "book_cost": 106004.0,
      "book_cost_per_unit": 48.47005029721079,
      "last_price": 50.3,
      "current_value": 110006.09999999999,
      "pl_pct": 3.78,
      "target_weight": 11.6,
      "auto_price": true,
      "price_updated": "2026-02-24T07:06:29.835152"
    },
    {
      "owner": "EF",
      "asset_type": "MA",
      "account": "SIPP",
      "ticker": "RCP",
      "name": "RIT Capital",
      "quantity": 1288.0,
      "book_cost": 23558.0,
      "book_cost_per_unit": 18.290372670807454,
      "last_price": 21.8,
      "current_value": 28078.4,
      "pl_pct": 19.19,
      "target_weight": 6.1,
      "auto_price": true,
      "price_updated": "2026-02-24T07:06:29.835152"
    },
    {
      "owner": "LF",
      "asset_type": "MA",
      "account": "SIPP",
      "ticker": "RCP",
      "name": "RIT Capital",
      "quantity": 1256.0,
      "book_cost": 25183.0,
      "book_cost_per_unit": 20.05015923566879,
      "last_price": 21.8,
      "current_value": 27380.8,
      "pl_pct": 8.73,
      "target_weight": 0.0,
      "auto_price": true,
      "price_updated": "2026-02-24T07:06:29.835152"
    },
    {
      "owner": "EF",
      "asset_type": "MA",
      "account": "SIPP",
      "ticker": "RICA",
      "name": "Ruffer",
      "quantity": 36421.0,
      "book_cost": 104346.0,
      "book_cost_per_unit": 2.8649954696466327,
      "last_price": 3.06,
      "current_value": 111448.26,
      "pl_pct": 6.81,
      "target_weight": 11.5,
      "auto_price": true,
      "price_updated": "2026-02-24T07:06:29.835152"
    },
    {
      "owner": "EF",
      "asset_type": "MA",
      "account": "ISA",
      "ticker": "BHMG",
      "name": "BH Macro",
      "quantity": 10249.0,
      "book_cost": 40176.0,
      "book_cost_per_unit": 3.9199921943604252,
      "last_price": 4.27,
      "current_value": 43763.229999999996,
      "pl_pct": 8.93,
      "target_weight": 4.4,
      "auto_price": true,
      "price_updated": "2026-02-24T07:06:29.835152"
    },
    {
      "owner": "LF",
      "asset_type": "FI",
      "account": "SIPP",
      "ticker": "INXG",
      "name": "iShares Â£ Index-Lnkd Gilts ETF GBP Dist",
      "quantity": 3076.0,
      "book_cost": 36112.0,
      "book_cost_per_unit": 11.739921976592978,
      "last_price": 11.67199993133545,
      "current_value": 35903.07178878784,
      "pl_pct": -0.58,
      "target_weight": 3.7,
      "auto_price": true,
      "price_updated": "2026-02-24T07:06:29.835152"
    },
    {
      "owner": "LF",
      "asset_type": "FI",
      "account": "ISA",
      "ticker": "ITPG",
      "name": "iShares $ TIPS ETF GBP H Dist",
      "quantity": 11026.0,
      "book_cost": 54468.0,
      "book_cost_per_unit": 4.939960094322511,
      "last_price": 4.848999977111816,
      "current_value": 53465.07374763489,
      "pl_pct": -1.84,
      "target_weight": 5.7,
      "auto_price": true,
      "price_updated": "2026-02-24T07:06:29.835152"
    },
    {
      "owner": "LF",
      "asset_type": "AA",
      "account": "SIPP",
      "ticker": "SGLN",
      "name": "Ishares Gold",
      "quantity": 1461.0,
      "book_cost": 69894.0,
      "book_cost_per_unit": 47.83983572895277,
      "last_price": 74.91,
      "current_value": 109443.51,
      "pl_pct": 56.58,
      "target_weight": 10.5,
      "auto_price": true,
      "price_updated": "2026-02-24T07:06:29.835152"
    },
    {
      "owner": "LF",
      "asset_type": "AA",
      "account": "SIPP",
      "ticker": "TRY",
      "name": "TR Property",
      "quantity": 16332.0,
      "book_cost": 51119.0,
      "book_cost_per_unit": 3.1299902032819005,
      "last_price": 3.53,
      "current_value": 57651.96,
      "pl_pct": 12.78,
      "target_weight": 5.5,
      "auto_price": true,
      "price_updated": "2026-02-24T07:06:29.835152"
    },
    {
      "owner": "LF",
      "asset_type": "EQ",
      "account": "ISA",
      "ticker": "BVYPNY2",
      "name": "Guinness Global Equity Income Y GBP Acc",
      "quantity": 1527.69,
      "last_price": 31.61,
      "book_cost": 48000.0,
      "target_weight": 0,
      "current_value": 48290.2809,
      "pl_pct": 0.6,
      "auto_price": true,
      "price_updated": "2026-02-24T07:11:52.063928",
      "book_cost_per_unit": 31.42
    }
  ],
  "cash_balances": {
    "Ed Forrester SIPP": 1370,
    "Ed Forrester ISA": 19019,
    "Lucy Forrester SIPP": 266,
    "Lucy Forrester ISA": 11562
  },
  "cash_target_percentage": 7.6
}